notonames/__init__.py
notonames/notonames.py
notonames-0.0.3.dist-info/licenses/LICENSE
notonames-0.0.3.dist-info/METADATA
notonames-0.0.3.dist-info/WHEEL
notonames-0.0.3.dist-info/entry_points.txt
notonames-0.0.3.dist-info/top_level.txt
notonames-0.0.3.dist-info/RECORD
