Metadata-Version: 2.4
Name: notonames
Version: 0.0.3
Summary: Checks for noto-emoji style filenames
Author: Rod S
Author-email: rsheeter@google.com
Requires-Python: >=3.9
License-File: LICENSE
Requires-Dist: absl-py>=2.3.1
Provides-Extra: dev
Requires-Dist: pytest; extra == "dev"
Requires-Dist: black==25.1.0; extra == "dev"
Dynamic: author
Dynamic: author-email
Dynamic: license-file
Dynamic: provides-extra
Dynamic: requires-dist
Dynamic: requires-python
Dynamic: summary
